Metadata-Version: 1.1
Name: unisquid
Version: 1.0.1
Summary: Yet another unittest extension for python.
Home-page: https://github.com/beylsp/unisquid
Author: Patrik Beyls
Author-email: UNKNOWN
License: MIT
Download-URL: https://github.com/beylsp/unisquid/tarball/1.0.1
Keywords: testing
Platform: UNKNOWN
Classifier: Development Status :: 3 - Alpha
Classifier: Intended Audience :: Developers
Classifier: Programming Language :: Python
Classifier: Programming Language :: Python :: 2
Classifier: Programming Language :: Python :: 2.7
Classifier: Programming Language :: Python :: 3
Classifier: Programming Language :: Python :: 3.3
Classifier: Programming Language :: Python :: 3.4
